odoo9_addon_web_dashboard_tile-9.0.1.1.0-py2.7-nspkg.pth
odoo9_addon_web_dashboard_tile-9.0.1.1.0.dist-info/DESCRIPTION.rst
odoo9_addon_web_dashboard_tile-9.0.1.1.0.dist-info/METADATA
odoo9_addon_web_dashboard_tile-9.0.1.1.0.dist-info/RECORD
odoo9_addon_web_dashboard_tile-9.0.1.1.0.dist-info/WHEEL
odoo9_addon_web_dashboard_tile-9.0.1.1.0.dist-info/metadata.json
odoo9_addon_web_dashboard_tile-9.0.1.1.0.dist-info/namespace_packages.txt
odoo9_addon_web_dashboard_tile-9.0.1.1.0.dist-info/top_level.txt
odoo_addons/web_dashboard_tile/README.rst
odoo_addons/web_dashboard_tile/__init__.py
odoo_addons/web_dashboard_tile/__openerp__.py
odoo_addons/web_dashboard_tile/demo/res_groups.yml
odoo_addons/web_dashboard_tile/demo/tile_category.yml
odoo_addons/web_dashboard_tile/demo/tile_tile.yml
odoo_addons/web_dashboard_tile/i18n/ar.po
odoo_addons/web_dashboard_tile/i18n/ca.po
odoo_addons/web_dashboard_tile/i18n/de.po
odoo_addons/web_dashboard_tile/i18n/es.po
odoo_addons/web_dashboard_tile/i18n/fi.po
odoo_addons/web_dashboard_tile/i18n/fr.po
odoo_addons/web_dashboard_tile/i18n/it.po
odoo_addons/web_dashboard_tile/i18n/nl.po
odoo_addons/web_dashboard_tile/i18n/pt_BR.po
odoo_addons/web_dashboard_tile/i18n/sl.po
odoo_addons/web_dashboard_tile/i18n/tr.po
odoo_addons/web_dashboard_tile/i18n/web_dashboard_tile.pot
odoo_addons/web_dashboard_tile/migrations/8.0.3.0/post-migration.py
odoo_addons/web_dashboard_tile/migrations/8.0.4.0/post-migration.py
odoo_addons/web_dashboard_tile/models/__init__.py
odoo_addons/web_dashboard_tile/models/tile_category.py
odoo_addons/web_dashboard_tile/models/tile_tile.py
odoo_addons/web_dashboard_tile/security/ir.model.access.csv
odoo_addons/web_dashboard_tile/security/rules.xml
odoo_addons/web_dashboard_tile/static/description/icon.png
odoo_addons/web_dashboard_tile/static/src/css/tile.css
odoo_addons/web_dashboard_tile/static/src/img/avg.png
odoo_addons/web_dashboard_tile/static/src/img/max.png
odoo_addons/web_dashboard_tile/static/src/img/median.png
odoo_addons/web_dashboard_tile/static/src/img/min.png
odoo_addons/web_dashboard_tile/static/src/img/screenshot_action_click.png
odoo_addons/web_dashboard_tile/static/src/img/screenshot_dashboard.png
odoo_addons/web_dashboard_tile/static/src/img/sum.png
odoo_addons/web_dashboard_tile/static/src/js/custom_js.js
odoo_addons/web_dashboard_tile/static/src/xml/custom_xml.xml
